{
  "name": "Workflow 1: Auto Job Applications + Status Tracking",
  "nodes": [
    {
      "parameters": {
        "rule": {
          "interval": [
            {
              "field": "cronExpression",
              "expression": "0 9 * * *"
            }
          ]
        }
      },
      "id": "schedule-trigger",
      "name": "Schedule Trigger",
      "type": "n8n-nodes-base.scheduleTrigger",
      "typeVersion": 1.1,
      "position": [240, 300]
    },
    {
      "parameters": {
        "operation": "read",
        "documentId": {
          "__rl": true,
          "value": "YOUR_SPREADSHEET_ID",
          "mode": "id"
        },
        "sheetName": {
          "__rl": true,
          "value": "Job Applications",
          "mode": "name"
        },
        "options": {
          "range": ""
        }
      },
      "id": "google-sheets-read",
      "name": "Read Job List",
      "type": "n8n-nodes-base.googleSheets",
      "typeVersion": 4.2,
      "position": [460, 300],
      "credentials": {
        "googleSheetsOAuth2Api": {
          "id": "YOUR_GOOGLE_SHEETS_CREDENTIAL_ID",
          "name": "Google Sheets account"
        }
      }
    },
    {
      "parameters": {
        "conditions": {
          "string": [
            {
              "value1": "={{ $json.Status }}",
              "operation": "equals",
              "value2": "Not Applied"
            }
          ]
        }
      },
      "id": "filter-not-applied",
      "name": "Filter Not Applied",
      "type": "n8n-nodes-base.if",
      "typeVersion": 1,
      "position": [680, 300]
    },
    {
      "parameters": {
        "conditions": {
          "string": [
            {
              "value1": "={{ $json.Platform }}",
              "operation": "equals",
              "value2": "LinkedIn"
            }
          ]
        }
      },
      "id": "check-platform",
      "name": "Check Platform",
      "type": "n8n-nodes-base.switch",
      "typeVersion": 1,
      "position": [900, 300]
    },
    {
      "parameters": {
        "url": "={{ $json['Job URL'] }}",
        "method": "POST",
        "sendBody": true,
        "bodyParameters": {
          "parameters": [
            {
              "name": "resumeUrl",
              "value": "={{ $json['Resume URL'] }}"
            },
            {
              "name": "coverLetter",
              "value": "={{ $json['Cover Letter'] }}"
            }
          ]
        },
        "options": {}
      },
      "id": "apply-to-job-linkedin",
      "name": "Apply to Job (LinkedIn)",
      "type": "n8n-nodes-base.httpRequest",
      "typeVersion": 4.1,
      "position": [1120, 180]
    },
    {
      "parameters": {
        "url": "={{ $json['Job URL'] }}",
        "method": "POST",
        "sendBody": true,
        "bodyParameters": {
          "parameters": [
            {
              "name": "resumeUrl",
              "value": "={{ $json['Resume URL'] }}"
            },
            {
              "name": "coverLetter",
              "value": "={{ $json['Cover Letter'] }}"
            }
          ]
        },
        "options": {}
      },
      "id": "apply-to-job-indeed",
      "name": "Apply to Job (Indeed)",
      "type": "n8n-nodes-base.httpRequest",
      "typeVersion": 4.1,
      "position": [1120, 300]
    },
    {
      "parameters": {
        "url": "={{ $json['Job URL'] }}",
        "method": "POST",
        "sendBody": true,
        "bodyParameters": {
          "parameters": [
            {
              "name": "resumeUrl",
              "value": "={{ $json['Resume URL'] }}"
            },
            {
              "name": "coverLetter",
              "value": "={{ $json['Cover Letter'] }}"
            }
          ]
        },
        "options": {}
      },
      "id": "apply-to-job-other",
      "name": "Apply to Job (Other)",
      "type": "n8n-nodes-base.httpRequest",
      "typeVersion": 4.1,
      "position": [1120, 420]
    },
    {
      "parameters": {
        "jsCode": "const currentDate = new Date().toISOString().split('T')[0];\nconst applicationId = `APP-${Date.now()}-${Math.random().toString(36).substr(2, 9)}`;\n\nreturn [\n  {\n    json: {\n      ...items[0].json,\n      'Applied Date': currentDate,\n      'Status': 'Applied',\n      'Application ID': applicationId,\n      'Last Updated': currentDate\n    }\n  }\n];"
      },
      "id": "format-response",
      "name": "Format Response",
      "type": "n8n-nodes-base.code",
      "typeVersion": 2,
      "position": [1340, 300]
    },
    {
      "parameters": {
        "operation": "update",
        "documentId": {
          "__rl": true,
          "value": "YOUR_SPREADSHEET_ID",
          "mode": "id"
        },
        "sheetName": {
          "__rl": true,
          "value": "Job Applications",
          "mode": "name"
        },
        "columns": {
          "mappingMode": "autoMapInputData",
          "matchingColumns": ["Job Title", "Company"],
          "schema": [
            {
              "id": "Status",
              "displayName": "Status",
              "required": false,
              "defaultMatch": false,
              "display": true,
              "type": "string",
              "canBeUsedToMatch": true
            },
            {
              "id": "Applied Date",
              "displayName": "Applied Date",
              "required": false,
              "defaultMatch": false,
              "display": true,
              "type": "string",
              "canBeUsedToMatch": false
            },
            {
              "id": "Application ID",
              "displayName": "Application ID",
              "required": false,
              "defaultMatch": false,
              "display": true,
              "type": "string",
              "canBeUsedToMatch": false
            },
            {
              "id": "Last Updated",
              "displayName": "Last Updated",
              "required": false,
              "defaultMatch": false,
              "display": true,
              "type": "string",
              "canBeUsedToMatch": false
            }
          ]
        },
        "options": {}
      },
      "id": "update-google-sheets",
      "name": "Update Google Sheets",
      "type": "n8n-nodes-base.googleSheets",
      "typeVersion": 4.2,
      "position": [1560, 300],
      "credentials": {
        "googleSheetsOAuth2Api": {
          "id": "YOUR_GOOGLE_SHEETS_CREDENTIAL_ID",
          "name": "Google Sheets account"
        }
      }
    },
    {
      "parameters": {
        "sendTo": "YOUR_EMAIL@example.com",
        "subject": "Job Application Submitted: {{ $json['Job Title'] }} at {{ $json.Company }}",
        "message": "=Hello,\n\nYour application has been successfully submitted:\n\n**Job Title:** {{ $json['Job Title'] }}\n**Company:** {{ $json.Company }}\n**Platform:** {{ $json.Platform }}\n**Application ID:** {{ $json['Application ID'] }}\n**Applied Date:** {{ $json['Applied Date'] }}\n**Job URL:** {{ $json['Job URL'] }}\n\nGood luck with your application!\n\nBest regards,\nYour Job Automation System",
        "options": {}
      },
      "id": "send-email-notification",
      "name": "Send Email Notification",
      "type": "n8n-nodes-base.gmail",
      "typeVersion": 2.1,
      "position": [1780, 300],
      "credentials": {
        "gmailOAuth2": {
          "id": "YOUR_GMAIL_CREDENTIAL_ID",
          "name": "Gmail account"
        }
      }
    },
    {
      "parameters": {
        "rule": {
          "interval": [
            {
              "field": "cronExpression",
              "expression": "0 10 */2 * *"
            }
          ]
        }
      },
      "id": "status-check-trigger",
      "name": "Status Check (Every 2 Days)",
      "type": "n8n-nodes-base.scheduleTrigger",
      "typeVersion": 1.1,
      "position": [240, 600]
    },
    {
      "parameters": {
        "operation": "read",
        "documentId": {
          "__rl": true,
          "value": "YOUR_SPREADSHEET_ID",
          "mode": "id"
        },
        "sheetName": {
          "__rl": true,
          "value": "Job Applications",
          "mode": "name"
        },
        "options": {}
      },
      "id": "read-applied-jobs",
      "name": "Read Applied Jobs",
      "type": "n8n-nodes-base.googleSheets",
      "typeVersion": 4.2,
      "position": [460, 600],
      "credentials": {
        "googleSheetsOAuth2Api": {
          "id": "YOUR_GOOGLE_SHEETS_CREDENTIAL_ID",
          "name": "Google Sheets account"
        }
      }
    },
    {
      "parameters": {
        "conditions": {
          "string": [
            {
              "value1": "={{ $json.Status }}",
              "operation": "equals",
              "value2": "Applied"
            }
          ]
        }
      },
      "id": "filter-applied-status",
      "name": "Filter Applied Status",
      "type": "n8n-nodes-base.if",
      "typeVersion": 1,
      "position": [680, 600]
    },
    {
      "parameters": {
        "url": "={{ $json['Job URL'] }}/status",
        "method": "GET",
        "options": {}
      },
      "id": "check-application-status",
      "name": "Check Application Status",
      "type": "n8n-nodes-base.httpRequest",
      "typeVersion": 4.1,
      "position": [900, 600]
    },
    {
      "parameters": {
        "jsCode": "const statusMap = {\n  'under_review': 'Under Review',\n  'interview': 'Interview',\n  'rejected': 'Rejected',\n  'offer': 'Offer',\n  'pending': 'Applied'\n};\n\nconst currentDate = new Date().toISOString().split('T')[0];\nconst apiStatus = items[0].json.status || 'pending';\nconst newStatus = statusMap[apiStatus] || 'Applied';\n\nreturn [\n  {\n    json: {\n      ...items[0].json,\n      'Status': newStatus,\n      'Last Updated': currentDate\n    }\n  }\n];"
      },
      "id": "parse-status",
      "name": "Parse Status",
      "type": "n8n-nodes-base.code",
      "typeVersion": 2,
      "position": [1120, 600]
    },
    {
      "parameters": {
        "operation": "update",
        "documentId": {
          "__rl": true,
          "value": "YOUR_SPREADSHEET_ID",
          "mode": "id"
        },
        "sheetName": {
          "__rl": true,
          "value": "Job Applications",
          "mode": "name"
        },
        "columns": {
          "mappingMode": "autoMapInputData",
          "matchingColumns": ["Application ID"],
          "schema": [
            {
              "id": "Status",
              "displayName": "Status",
              "required": false,
              "defaultMatch": false,
              "display": true,
              "type": "string",
              "canBeUsedToMatch": true
            },
            {
              "id": "Last Updated",
              "displayName": "Last Updated",
              "required": false,
              "defaultMatch": false,
              "display": true,
              "type": "string",
              "canBeUsedToMatch": false
            }
          ]
        },
        "options": {}
      },
      "id": "update-status-sheet",
      "name": "Update Status in Sheet",
      "type": "n8n-nodes-base.googleSheets",
      "typeVersion": 4.2,
      "position": [1340, 600],
      "credentials": {
        "googleSheetsOAuth2Api": {
          "id": "YOUR_GOOGLE_SHEETS_CREDENTIAL_ID",
          "name": "Google Sheets account"
        }
      }
    },
    {
      "parameters": {
        "conditions": {
          "string": [
            {
              "value1": "={{ $json.Status }}",
              "operation": "regex",
              "value2": "Interview|Rejected|Offer"
            }
          ]
        }
      },
      "id": "filter-important-updates",
      "name": "Filter Important Updates",
      "type": "n8n-nodes-base.if",
      "typeVersion": 1,
      "position": [1560, 600]
    },
    {
      "parameters": {
        "sendTo": "YOUR_EMAIL@example.com",
        "subject": "🔔 Application Status Update: {{ $json['Job Title'] }} - {{ $json.Status }}",
        "message": "=Hello,\n\nYour application status has been updated:\n\n**Job Title:** {{ $json['Job Title'] }}\n**Company:** {{ $json.Company }}\n**New Status:** {{ $json.Status }}\n**Application ID:** {{ $json['Application ID'] }}\n**Last Updated:** {{ $json['Last Updated'] }}\n**Job URL:** {{ $json['Job URL'] }}\n\n{% if $json.Status === 'Interview' %}\n🎉 Congratulations! You've been invited for an interview.\n{% elif $json.Status === 'Offer' %}\n🎊 Amazing! You've received a job offer!\n{% elif $json.Status === 'Rejected' %}\nDon't give up! Keep applying to more opportunities.\n{% endif %}\n\nBest regards,\nYour Job Automation System",
        "options": {}
      },
      "id": "send-status-email",
      "name": "Send Status Email",
      "type": "n8n-nodes-base.gmail",
      "typeVersion": 2.1,
      "position": [1780, 600],
      "credentials": {
        "gmailOAuth2": {
          "id": "YOUR_GMAIL_CREDENTIAL_ID",
          "name": "Gmail account"
        }
      }
    }
  ],
  "connections": {
    "Schedule Trigger": {
      "main": [
        [
          {
            "node": "Read Job List",
            "type": "main",
            "index": 0
          }
        ]
      ]
    },
    "Read Job List": {
      "main": [
        [
          {
            "node": "Filter Not Applied",
            "type": "main",
            "index": 0
          }
        ]
      ]
    },
    "Filter Not Applied": {
      "main": [
        [
          {
            "node": "Check Platform",
            "type": "main",
            "index": 0
          }
        ]
      ]
    },
    "Check Platform": {
      "main": [
        [
          {
            "node": "Apply to Job (LinkedIn)",
            "type": "main",
            "index": 0
          }
        ],
        [
          {
            "node": "Apply to Job (Indeed)",
            "type": "main",
            "index": 0
          }
        ],
        [
          {
            "node": "Apply to Job (Other)",
            "type": "main",
            "index": 0
          }
        ]
      ]
    },
    "Apply to Job (LinkedIn)": {
      "main": [
        [
          {
            "node": "Format Response",
            "type": "main",
            "index": 0
          }
        ]
      ]
    },
    "Apply to Job (Indeed)": {
      "main": [
        [
          {
            "node": "Format Response",
            "type": "main",
            "index": 0
          }
        ]
      ]
    },
    "Apply to Job (Other)": {
      "main": [
        [
          {
            "node": "Format Response",
            "type": "main",
            "index": 0
          }
        ]
      ]
    },
    "Format Response": {
      "main": [
        [
          {
            "node": "Update Google Sheets",
            "type": "main",
            "index": 0
          }
        ]
      ]
    },
    "Update Google Sheets": {
      "main": [
        [
          {
            "node": "Send Email Notification",
            "type": "main",
            "index": 0
          }
        ]
      ]
    },
    "Status Check (Every 2 Days)": {
      "main": [
        [
          {
            "node": "Read Applied Jobs",
            "type": "main",
            "index": 0
          }
        ]
      ]
    },
    "Read Applied Jobs": {
      "main": [
        [
          {
            "node": "Filter Applied Status",
            "type": "main",
            "index": 0
          }
        ]
      ]
    },
    "Filter Applied Status": {
      "main": [
        [
          {
            "node": "Check Application Status",
            "type": "main",
            "index": 0
          }
        ]
      ]
    },
    "Check Application Status": {
      "main": [
        [
          {
            "node": "Parse Status",
            "type": "main",
            "index": 0
          }
        ]
      ]
    },
    "Parse Status": {
      "main": [
        [
          {
            "node": "Update Status in Sheet",
            "type": "main",
            "index": 0
          }
        ]
      ]
    },
    "Update Status in Sheet": {
      "main": [
        [
          {
            "node": "Filter Important Updates",
            "type": "main",
            "index": 0
          }
        ]
      ]
    },
    "Filter Important Updates": {
      "main": [
        [
          {
            "node": "Send Status Email",
            "type": "main",
            "index": 0
          }
        ]
      ]
    }
  },
  "settings": {
    "executionOrder": "v1"
  },
  "staticData": null,
  "tags": [],
  "triggerCount": 0,
  "updatedAt": "2024-01-01T00:00:00.000Z",
  "versionId": "1"
}
